inspiral/__init__.py
inspiral/inspiral.py
inspiral-0.0.1.dist-info/LICENSE
inspiral-0.0.1.dist-info/METADATA
inspiral-0.0.1.dist-info/WHEEL
inspiral-0.0.1.dist-info/top_level.txt
inspiral-0.0.1.dist-info/RECORD
