Metadata-Version: 2.1
Name: inspiral
Version: 0.0.1
Summary: inspiral
Author-email: Matthew Mould <mattdmould@gmail.com>
Project-URL: Homepage, https://github.com/mdmould/inspiral
Classifier: Programming Language :: Python :: 3
Classifier: License :: OSI Approved :: MIT License
Classifier: Operating System :: OS Independent
Requires-Python: >=3.9
License-File: LICENSE
